endf_parserpy/__init__.py
endf_parserpy/endf_parser_base.py
endf_parserpy/endf_parser_factory.py
endf_parserpy/cli/__init__.py
endf_parserpy/cli/cmd.py
endf_parserpy/cli/cmd_utils.py
endf_parserpy/cli/actions/__init__.py
endf_parserpy/cli/actions/compare.py
endf_parserpy/cli/actions/convert.py
endf_parserpy/cli/actions/explain.py
endf_parserpy/cli/actions/insert_text.py
endf_parserpy/cli/actions/match.py
endf_parserpy/cli/actions/replace.py
endf_parserpy/cli/actions/show.py
endf_parserpy/cli/actions/update_directory.py
endf_parserpy/cli/actions/validate.py
endf_parserpy/compat_wrappers/__init__.py
endf_parserpy/compat_wrappers/import_resources_new.py
endf_parserpy/compat_wrappers/importlib_resources.py
endf_parserpy/compiler/__init__.py
endf_parserpy/compiler/code_generator_core.py
endf_parserpy/compiler/code_generator_parsing.py
endf_parserpy/compiler/code_generator_parsing_core.py
endf_parserpy/compiler/code_generator_writing.py
endf_parserpy/compiler/code_generator_writing_core.py
endf_parserpy/compiler/compiler.py
endf_parserpy/compiler/cpp_boilerplate.py
endf_parserpy/compiler/cpp_boilerplate_reading.py
endf_parserpy/compiler/cpp_boilerplate_writing.py
endf_parserpy/compiler/cpp_primitives.py
endf_parserpy/compiler/endf2cpp.py
endf_parserpy/compiler/endf2cpp_aux.py
endf_parserpy/compiler/endf2cpp_aux_writing.py
endf_parserpy/compiler/lookahead_management.py
endf_parserpy/compiler/mode_management.py
endf_parserpy/compiler/node_aux.py
endf_parserpy/compiler/node_checks.py
endf_parserpy/compiler/variable_management.py
endf_parserpy/compiler/cpp_templates/__init__.py
endf_parserpy/compiler/cpp_templates/endf_float_cpp.hpp
endf_parserpy/compiler/cpp_templates/index_shifter.hpp
endf_parserpy/compiler/cpp_templates/module_header.hpp
endf_parserpy/compiler/cpp_templates/module_header_reading.hpp
endf_parserpy/compiler/cpp_templates/module_header_writing.hpp
endf_parserpy/compiler/cpp_types/__init__.py
endf_parserpy-0.15.0.dist-info/LICENSE
endf_parserpy-0.15.0.dist-info/METADATA
endf_parserpy-0.15.0.dist-info/WHEEL
endf_parserpy-0.15.0.dist-info/entry_points.txt
endf_parserpy-0.15.0.dist-info/top_level.txt
endf_parserpy-0.15.0.dist-info/RECORD
endf_parserpy-0.15.0.dist-info/sboms/auditwheel.cdx.json
