Metadata-Version: 2.2
Name: endf-parserpy
Version: 0.15.0
Summary: A Python package for reading, writing, verifying and translating ENDF-6 files
Author: Georg Schnabel
License: MIT
Project-URL: Repository, https://github.com/iaea-nds/endf-parserpy
Project-URL: Documentation, https://endf-parserpy.readthedocs.io/en/stable/
Project-URL: Issues, https://github.com/iaea-nds/endf-parserpy/issues
Classifier: Development Status :: 4 - Beta
Classifier: Intended Audience :: Developers
Classifier: Intended Audience :: Science/Research
Classifier: Intended Audience :: End Users/Desktop
Classifier: Operating System :: OS Independent
Classifier: Operating System :: Microsoft :: Windows
Classifier: Operating System :: MacOS :: MacOS X
Classifier: Operating System :: POSIX :: Linux
Classifier: Programming Language :: Python :: 3
Classifier: Programming Language :: Python :: 3.8
Classifier: Programming Language :: Python :: 3.9
Classifier: Programming Language :: Python :: 3.10
Classifier: Programming Language :: Python :: 3.11
Classifier: Programming Language :: Python :: 3.12
Classifier: Programming Language :: Python :: 3.13
Requires-Python: >=3.8
License-File: LICENSE
Requires-Dist: lark>=1.0.0
Requires-Dist: platformdirs>=4.3.6
Dynamic: requires-dist
